sabdab_cli/__init__.py
sabdab_cli/cli.py
sabdab_cli/downloader/__init__.py
sabdab_cli/downloader/core.py
sabdab_cli/downloader/py.typed
sabdab_cli/downloader/runner.py
sabdab_cli/downloader/tasks.py
sabdab_cli/py.typed
sabdab_cli/summary.py
sabdab_cli/urls.py
sabdab_cli/utils.py
sabdab_cli-0.2.0.dist-info/WHEEL
sabdab_cli-0.2.0.dist-info/entry_points.txt
sabdab_cli-0.2.0.dist-info/METADATA
sabdab_cli-0.2.0.dist-info/RECORD
