Metadata-Version: 2.3
Name: sabdab-cli
Version: 0.2.0
Summary: A CLI for downloading SAbDab data.
Keywords: antibody,sabdab,cli,downloader
Author: Syafiq Kamarul Azman
Author-email: Syafiq Kamarul Azman <syafiqkamarulazman@gmail.com>
License: MIT
Classifier: Development Status :: 4 - Beta
Classifier: Intended Audience :: Science/Research
Classifier: License :: OSI Approved :: MIT License
Classifier: Programming Language :: Python :: 3
Classifier: Programming Language :: Python :: 3.10
Classifier: Programming Language :: Python :: 3.11
Classifier: Programming Language :: Python :: 3.12
Classifier: Topic :: Scientific/Engineering :: Bio-Informatics
Requires-Dist: typer>=0.20.0
Requires-Dist: rich>=14.2.0
Requires-Dist: httpx>=0.28.1
Requires-Dist: tenacity>=9.1.2
Requires-Dist: httpx[http2]>=0.28.1 ; extra == 'http2'
Requires-Python: >=3.10
Project-URL: Issues, https://github.com/syaffers/sabdab-cli/issues
Project-URL: Repository, https://github.com/syaffers/sabdab-cli
Provides-Extra: http2
